{"base":{"$white":"rgb(217,230,242)","$white-light":"rgb(217,230,242)","$black":"rgb(13,25,38)","$black-light":"rgb(13,25,38)","$cursor-text":"rgb(217,230,242)","$cursor":"rgb(217,230,242)","$red":"rgb(184,122,122)","$red-light":"rgb(219,189,189)","$green":"rgb(122,184,122)","$green-light":"rgb(189,219,189)","$yellow":"rgb(184,184,122)","$yellow-light":"rgb(219,219,189)","$blue":"rgb(122,122,184)","$blue-light":"rgb(189,189,219)","$magenta":"rgb(184,122,184)","$magenta-light":"rgb(219,189,219)","$cyan":"rgb(122,184,184)","$cyan-light":"rgb(189,219,219)"},"specialCase":{}}