{
    "base": {
        "--white": "rgb(236,240,254)",
        "--white-light": "rgb(246,255,235)",
        "--black": "rgb(35,37,55)",
        "--black-light": "rgb(35,37,55)",
        "--cursor-text": "rgb(254,205,94)",
        "--cursor": "rgb(236,240,254)",
        "--red": "rgb(198,0,74)",
        "--red-light": "rgb(218,75,138)",
        "--green": "rgb(172,241,87)",
        "--green-light": "rgb(219,255,169)",
        "--yellow": "rgb(254,205,94)",
        "--yellow-light": "rgb(254,230,169)",
        "--blue": "rgb(82,95,184)",
        "--blue-light": "rgb(178,190,250)",
        "--magenta": "rgb(152,111,130)",
        "--magenta-light": "rgb(253,165,205)",
        "--cyan": "rgb(150,135,99)",
        "--cyan-light": "rgb(165,189,134)"
    },
    "specialCase": []
}